{
  "repoUrl": "https://github.com/entireio/skills.git",
  "owner": "entireio",
  "repo": "skills",
  "updatedAt": "2026-05-20T09:16:37.514Z",
  "skillCount": 5,
  "skills": [
    {
      "name": "explain",
      "description": "Explains the intent behind source code by finding original session transcripts. Use explain with a function, file, or line of code to understand why it exists.",
      "version": "0.0.0",
      "license": "",
      "creator": "",
      "compatibility": "",
      "allowedTools": [],
      "installUrl": "github:entireio/skills:skills/explain",
      "relPath": "skills/explain",
      "verified": true,
      "tokenCount": 724,
      "evalSummary": {
        "overallScore": 66,
        "grade": "C",
        "categories": [
          {
            "id": "structure",
            "name": "Structure & completeness",
            "score": 7,
            "max": 10
          },
          {
            "id": "description",
            "name": "Description quality",
            "score": 7,
            "max": 10
          },
          {
            "id": "prompt-engineering",
            "name": "Prompt engineering",
            "score": 5,
            "max": 10
          },
          {
            "id": "context-efficiency",
            "name": "Context efficiency",
            "score": 7,
            "max": 10
          },
          {
            "id": "safety",
            "name": "Safety & guardrails",
            "score": 7,
            "max": 10
          },
          {
            "id": "testability",
            "name": "Testability",
            "score": 3,
            "max": 10
          },
          {
            "id": "naming",
            "name": "Naming & conventions",
            "score": 10,
            "max": 10
          }
        ],
        "evaluatedAt": "2026-05-20T09:16:37.506Z",
        "evaluatedVersion": "0.0.0"
      },
      "evalSummaries": {
        "quality": {
          "providerId": "quality",
          "providerVersion": "1.0.0",
          "schemaVersion": 1,
          "passed": true,
          "overallScore": 66,
          "grade": "C",
          "categories": [
            {
              "id": "structure",
              "name": "Structure & completeness",
              "score": 7,
              "max": 10
            },
            {
              "id": "description",
              "name": "Description quality",
              "score": 7,
              "max": 10
            },
            {
              "id": "prompt-engineering",
              "name": "Prompt engineering",
              "score": 5,
              "max": 10
            },
            {
              "id": "context-efficiency",
              "name": "Context efficiency",
              "score": 7,
              "max": 10
            },
            {
              "id": "safety",
              "name": "Safety & guardrails",
              "score": 7,
              "max": 10
            },
            {
              "id": "testability",
              "name": "Testability",
              "score": 3,
              "max": 10
            },
            {
              "id": "naming",
              "name": "Naming & conventions",
              "score": 10,
              "max": 10
            }
          ],
          "evaluatedAt": "2026-05-20T09:16:37.506Z",
          "evaluatedVersion": "0.0.0"
        },
        "skill-best-practice": {
          "providerId": "skill-best-practice",
          "providerVersion": "1.1.0",
          "schemaVersion": 1,
          "passed": false,
          "overallScore": 69,
          "grade": "C",
          "categories": [
            {
              "id": "validation",
              "name": "Deterministic validation",
              "score": 9,
              "max": 13
            }
          ],
          "evaluatedAt": "2026-05-20T09:16:37.506Z",
          "evaluatedVersion": "0.0.0"
        }
      }
    },
    {
      "name": "search",
      "description": "Use when the user wants to find prior work, checkpoints, or agent conversations by topic, repo, branch, author, or recent time window",
      "version": "0.0.0",
      "license": "",
      "creator": "",
      "compatibility": "",
      "allowedTools": [],
      "installUrl": "github:entireio/skills:skills/search",
      "relPath": "skills/search",
      "verified": true,
      "tokenCount": 815,
      "evalSummary": {
        "overallScore": 66,
        "grade": "C",
        "categories": [
          {
            "id": "structure",
            "name": "Structure & completeness",
            "score": 7,
            "max": 10
          },
          {
            "id": "description",
            "name": "Description quality",
            "score": 7,
            "max": 10
          },
          {
            "id": "prompt-engineering",
            "name": "Prompt engineering",
            "score": 7,
            "max": 10
          },
          {
            "id": "context-efficiency",
            "name": "Context efficiency",
            "score": 7,
            "max": 10
          },
          {
            "id": "safety",
            "name": "Safety & guardrails",
            "score": 7,
            "max": 10
          },
          {
            "id": "testability",
            "name": "Testability",
            "score": 1,
            "max": 10
          },
          {
            "id": "naming",
            "name": "Naming & conventions",
            "score": 10,
            "max": 10
          }
        ],
        "evaluatedAt": "2026-05-20T09:16:37.507Z",
        "evaluatedVersion": "0.0.0"
      },
      "evalSummaries": {
        "quality": {
          "providerId": "quality",
          "providerVersion": "1.0.0",
          "schemaVersion": 1,
          "passed": true,
          "overallScore": 66,
          "grade": "C",
          "categories": [
            {
              "id": "structure",
              "name": "Structure & completeness",
              "score": 7,
              "max": 10
            },
            {
              "id": "description",
              "name": "Description quality",
              "score": 7,
              "max": 10
            },
            {
              "id": "prompt-engineering",
              "name": "Prompt engineering",
              "score": 7,
              "max": 10
            },
            {
              "id": "context-efficiency",
              "name": "Context efficiency",
              "score": 7,
              "max": 10
            },
            {
              "id": "safety",
              "name": "Safety & guardrails",
              "score": 7,
              "max": 10
            },
            {
              "id": "testability",
              "name": "Testability",
              "score": 1,
              "max": 10
            },
            {
              "id": "naming",
              "name": "Naming & conventions",
              "score": 10,
              "max": 10
            }
          ],
          "evaluatedAt": "2026-05-20T09:16:37.507Z",
          "evaluatedVersion": "0.0.0"
        },
        "skill-best-practice": {
          "providerId": "skill-best-practice",
          "providerVersion": "1.1.0",
          "schemaVersion": 1,
          "passed": false,
          "overallScore": 77,
          "grade": "C",
          "categories": [
            {
              "id": "validation",
              "name": "Deterministic validation",
              "score": 10,
              "max": 13
            }
          ],
          "evaluatedAt": "2026-05-20T09:16:37.507Z",
          "evaluatedVersion": "0.0.0"
        }
      }
    },
    {
      "name": "session-handoff",
      "description": "Use when the user wants to continue work from one agent in another agent, inspect recent sessions, or summarize a saved session or checkpoint for handoff",
      "version": "0.0.0",
      "license": "",
      "creator": "",
      "compatibility": "",
      "allowedTools": [],
      "installUrl": "github:entireio/skills:skills/session-handoff",
      "relPath": "skills/session-handoff",
      "verified": true,
      "tokenCount": 2572,
      "evalSummary": {
        "overallScore": 74,
        "grade": "C",
        "categories": [
          {
            "id": "structure",
            "name": "Structure & completeness",
            "score": 7,
            "max": 10
          },
          {
            "id": "description",
            "name": "Description quality",
            "score": 7,
            "max": 10
          },
          {
            "id": "prompt-engineering",
            "name": "Prompt engineering",
            "score": 9,
            "max": 10
          },
          {
            "id": "context-efficiency",
            "name": "Context efficiency",
            "score": 9,
            "max": 10
          },
          {
            "id": "safety",
            "name": "Safety & guardrails",
            "score": 7,
            "max": 10
          },
          {
            "id": "testability",
            "name": "Testability",
            "score": 3,
            "max": 10
          },
          {
            "id": "naming",
            "name": "Naming & conventions",
            "score": 10,
            "max": 10
          }
        ],
        "evaluatedAt": "2026-05-20T09:16:37.508Z",
        "evaluatedVersion": "0.0.0"
      },
      "evalSummaries": {
        "quality": {
          "providerId": "quality",
          "providerVersion": "1.0.0",
          "schemaVersion": 1,
          "passed": true,
          "overallScore": 74,
          "grade": "C",
          "categories": [
            {
              "id": "structure",
              "name": "Structure & completeness",
              "score": 7,
              "max": 10
            },
            {
              "id": "description",
              "name": "Description quality",
              "score": 7,
              "max": 10
            },
            {
              "id": "prompt-engineering",
              "name": "Prompt engineering",
              "score": 9,
              "max": 10
            },
            {
              "id": "context-efficiency",
              "name": "Context efficiency",
              "score": 9,
              "max": 10
            },
            {
              "id": "safety",
              "name": "Safety & guardrails",
              "score": 7,
              "max": 10
            },
            {
              "id": "testability",
              "name": "Testability",
              "score": 3,
              "max": 10
            },
            {
              "id": "naming",
              "name": "Naming & conventions",
              "score": 10,
              "max": 10
            }
          ],
          "evaluatedAt": "2026-05-20T09:16:37.508Z",
          "evaluatedVersion": "0.0.0"
        },
        "skill-best-practice": {
          "providerId": "skill-best-practice",
          "providerVersion": "1.1.0",
          "schemaVersion": 1,
          "passed": false,
          "overallScore": 77,
          "grade": "C",
          "categories": [
            {
              "id": "validation",
              "name": "Deterministic validation",
              "score": 10,
              "max": 13
            }
          ],
          "evaluatedAt": "2026-05-20T09:16:37.508Z",
          "evaluatedVersion": "0.0.0"
        }
      }
    },
    {
      "name": "session-to-skill",
      "description": "Use when the user wants to turn one or more Entire-tracked sessions, checkpoints, or repeated agent workflows into a reusable agent skill.",
      "version": "0.0.0",
      "license": "",
      "creator": "",
      "compatibility": "",
      "allowedTools": [],
      "installUrl": "github:entireio/skills:skills/session-to-skill",
      "relPath": "skills/session-to-skill",
      "verified": true,
      "tokenCount": 2425,
      "evalSummary": {
        "overallScore": 81,
        "grade": "B",
        "categories": [
          {
            "id": "structure",
            "name": "Structure & completeness",
            "score": 7,
            "max": 10
          },
          {
            "id": "description",
            "name": "Description quality",
            "score": 7,
            "max": 10
          },
          {
            "id": "prompt-engineering",
            "name": "Prompt engineering",
            "score": 10,
            "max": 10
          },
          {
            "id": "context-efficiency",
            "name": "Context efficiency",
            "score": 9,
            "max": 10
          },
          {
            "id": "safety",
            "name": "Safety & guardrails",
            "score": 10,
            "max": 10
          },
          {
            "id": "testability",
            "name": "Testability",
            "score": 6,
            "max": 10
          },
          {
            "id": "naming",
            "name": "Naming & conventions",
            "score": 8,
            "max": 10
          }
        ],
        "evaluatedAt": "2026-05-20T09:16:37.510Z",
        "evaluatedVersion": "0.0.0"
      },
      "evalSummaries": {
        "quality": {
          "providerId": "quality",
          "providerVersion": "1.0.0",
          "schemaVersion": 1,
          "passed": true,
          "overallScore": 81,
          "grade": "B",
          "categories": [
            {
              "id": "structure",
              "name": "Structure & completeness",
              "score": 7,
              "max": 10
            },
            {
              "id": "description",
              "name": "Description quality",
              "score": 7,
              "max": 10
            },
            {
              "id": "prompt-engineering",
              "name": "Prompt engineering",
              "score": 10,
              "max": 10
            },
            {
              "id": "context-efficiency",
              "name": "Context efficiency",
              "score": 9,
              "max": 10
            },
            {
              "id": "safety",
              "name": "Safety & guardrails",
              "score": 10,
              "max": 10
            },
            {
              "id": "testability",
              "name": "Testability",
              "score": 6,
              "max": 10
            },
            {
              "id": "naming",
              "name": "Naming & conventions",
              "score": 8,
              "max": 10
            }
          ],
          "evaluatedAt": "2026-05-20T09:16:37.510Z",
          "evaluatedVersion": "0.0.0"
        },
        "skill-best-practice": {
          "providerId": "skill-best-practice",
          "providerVersion": "1.1.0",
          "schemaVersion": 1,
          "passed": false,
          "overallScore": 77,
          "grade": "C",
          "categories": [
            {
              "id": "validation",
              "name": "Deterministic validation",
              "score": 10,
              "max": 13
            }
          ],
          "evaluatedAt": "2026-05-20T09:16:37.510Z",
          "evaluatedVersion": "0.0.0"
        }
      }
    },
    {
      "name": "what-happened",
      "description": "Explain why code looks the way it does by tracing the latest change for a file range or pasted snippet through `git blame` and deduplicated `entire explain` lookups. Use when the user asks what happened, says \"tell me why\" about a code block, is confused about a section of code, asks \"wtf is going on\", \"why is this like this\", \"why was this changed\", or wants provenance for a specific file block.",
      "version": "0.0.0",
      "license": "",
      "creator": "",
      "compatibility": "",
      "allowedTools": [],
      "installUrl": "github:entireio/skills:skills/what-happened",
      "relPath": "skills/what-happened",
      "verified": true,
      "tokenCount": 4469,
      "evalSummary": {
        "overallScore": 69,
        "grade": "C",
        "categories": [
          {
            "id": "structure",
            "name": "Structure & completeness",
            "score": 7,
            "max": 10
          },
          {
            "id": "description",
            "name": "Description quality",
            "score": 6,
            "max": 10
          },
          {
            "id": "prompt-engineering",
            "name": "Prompt engineering",
            "score": 7,
            "max": 10
          },
          {
            "id": "context-efficiency",
            "name": "Context efficiency",
            "score": 7,
            "max": 10
          },
          {
            "id": "safety",
            "name": "Safety & guardrails",
            "score": 6,
            "max": 10
          },
          {
            "id": "testability",
            "name": "Testability",
            "score": 5,
            "max": 10
          },
          {
            "id": "naming",
            "name": "Naming & conventions",
            "score": 10,
            "max": 10
          }
        ],
        "evaluatedAt": "2026-05-20T09:16:37.512Z",
        "evaluatedVersion": "0.0.0"
      },
      "evalSummaries": {
        "quality": {
          "providerId": "quality",
          "providerVersion": "1.0.0",
          "schemaVersion": 1,
          "passed": true,
          "overallScore": 69,
          "grade": "C",
          "categories": [
            {
              "id": "structure",
              "name": "Structure & completeness",
              "score": 7,
              "max": 10
            },
            {
              "id": "description",
              "name": "Description quality",
              "score": 6,
              "max": 10
            },
            {
              "id": "prompt-engineering",
              "name": "Prompt engineering",
              "score": 7,
              "max": 10
            },
            {
              "id": "context-efficiency",
              "name": "Context efficiency",
              "score": 7,
              "max": 10
            },
            {
              "id": "safety",
              "name": "Safety & guardrails",
              "score": 6,
              "max": 10
            },
            {
              "id": "testability",
              "name": "Testability",
              "score": 5,
              "max": 10
            },
            {
              "id": "naming",
              "name": "Naming & conventions",
              "score": 10,
              "max": 10
            }
          ],
          "evaluatedAt": "2026-05-20T09:16:37.512Z",
          "evaluatedVersion": "0.0.0"
        },
        "skill-best-practice": {
          "providerId": "skill-best-practice",
          "providerVersion": "1.1.0",
          "schemaVersion": 1,
          "passed": false,
          "overallScore": 69,
          "grade": "C",
          "categories": [
            {
              "id": "validation",
              "name": "Deterministic validation",
              "score": 9,
              "max": 13
            }
          ],
          "evaluatedAt": "2026-05-20T09:16:37.512Z",
          "evaluatedVersion": "0.0.0"
        }
      }
    }
  ],
  "bundles": [
    {
      "version": 1,
      "name": "entireio-skills-data-ai",
      "description": "Data, analytics, AI, model, prompt, agent, and automation skills. Derived from entireio/skills.",
      "author": "ASM (entireio/skills)",
      "createdAt": "2026-05-20T09:16:37.514Z",
      "tags": [
        "repo-derived",
        "inferred",
        "data",
        "ai",
        "agents",
        "entireio",
        "skills"
      ],
      "skills": [
        {
          "name": "explain",
          "installUrl": "github:entireio/skills:skills/explain",
          "description": "Explains the intent behind source code by finding original session transcripts. Use explain with a function, file, or line of code to understand why it exists.",
          "version": "0.0.0"
        },
        {
          "name": "search",
          "installUrl": "github:entireio/skills:skills/search",
          "description": "Use when the user wants to find prior work, checkpoints, or agent conversations by topic, repo, branch, author, or recent time window",
          "version": "0.0.0"
        },
        {
          "name": "session-handoff",
          "installUrl": "github:entireio/skills:skills/session-handoff",
          "description": "Use when the user wants to continue work from one agent in another agent, inspect recent sessions, or summarize a saved session or checkpoint for handoff",
          "version": "0.0.0"
        },
        {
          "name": "session-to-skill",
          "installUrl": "github:entireio/skills:skills/session-to-skill",
          "description": "Use when the user wants to turn one or more Entire-tracked sessions, checkpoints, or repeated agent workflows into a reusable agent skill.",
          "version": "0.0.0"
        },
        {
          "name": "what-happened",
          "installUrl": "github:entireio/skills:skills/what-happened",
          "description": "Explain why code looks the way it does by tracing the latest change for a file range or pasted snippet through `git blame` and deduplicated `entire explain` lookups. Use when the user asks what happened, says \"tell me why\" about a code block, is confused about a section of code, asks \"wtf is going on\", \"why is this like this\", \"why was this changed\", or wants provenance for a specific file block.",
          "version": "0.0.0"
        }
      ],
      "sourceRepo": {
        "owner": "entireio",
        "repo": "skills",
        "repoUrl": "https://github.com/entireio/skills.git"
      },
      "inferred": true
    },
    {
      "version": 1,
      "name": "entireio-skills-devops",
      "description": "Deployment, CI/CD, infrastructure, cloud, Docker, Kubernetes, and automation skills. Derived from entireio/skills.",
      "author": "ASM (entireio/skills)",
      "createdAt": "2026-05-20T09:16:37.514Z",
      "tags": [
        "repo-derived",
        "inferred",
        "devops",
        "infra",
        "automation",
        "entireio",
        "skills"
      ],
      "skills": [
        {
          "name": "session-to-skill",
          "installUrl": "github:entireio/skills:skills/session-to-skill",
          "description": "Use when the user wants to turn one or more Entire-tracked sessions, checkpoints, or repeated agent workflows into a reusable agent skill.",
          "version": "0.0.0"
        },
        {
          "name": "what-happened",
          "installUrl": "github:entireio/skills:skills/what-happened",
          "description": "Explain why code looks the way it does by tracing the latest change for a file range or pasted snippet through `git blame` and deduplicated `entire explain` lookups. Use when the user asks what happened, says \"tell me why\" about a code block, is confused about a section of code, asks \"wtf is going on\", \"why is this like this\", \"why was this changed\", or wants provenance for a specific file block.",
          "version": "0.0.0"
        }
      ],
      "sourceRepo": {
        "owner": "entireio",
        "repo": "skills",
        "repoUrl": "https://github.com/entireio/skills.git"
      },
      "inferred": true
    },
    {
      "version": 1,
      "name": "entireio-skills-engineering",
      "description": "Coding, debugging, testing, architecture, review, and software engineering skills. Derived from entireio/skills.",
      "author": "ASM (entireio/skills)",
      "createdAt": "2026-05-20T09:16:37.514Z",
      "tags": [
        "repo-derived",
        "inferred",
        "engineering",
        "coding",
        "testing",
        "entireio",
        "skills"
      ],
      "skills": [
        {
          "name": "explain",
          "installUrl": "github:entireio/skills:skills/explain",
          "description": "Explains the intent behind source code by finding original session transcripts. Use explain with a function, file, or line of code to understand why it exists.",
          "version": "0.0.0"
        },
        {
          "name": "what-happened",
          "installUrl": "github:entireio/skills:skills/what-happened",
          "description": "Explain why code looks the way it does by tracing the latest change for a file range or pasted snippet through `git blame` and deduplicated `entire explain` lookups. Use when the user asks what happened, says \"tell me why\" about a code block, is confused about a section of code, asks \"wtf is going on\", \"why is this like this\", \"why was this changed\", or wants provenance for a specific file block.",
          "version": "0.0.0"
        }
      ],
      "sourceRepo": {
        "owner": "entireio",
        "repo": "skills",
        "repoUrl": "https://github.com/entireio/skills.git"
      },
      "inferred": true
    }
  ]
}
